{
    "rounds": [
        1,
        2,
        3,
        4,
        5,
        6,
        7,
        8,
        9,
        10,
        11,
        12,
        13,
        14,
        15
    ],
    "accuracy": [
        0.1737,
        0.1737,
        0.1737,
        0.1737,
        0.1737,
        0.1737,
        0.1737,
        0.1737,
        0.1737,
        0.1737,
        0.1737,
        0.1737,
        0.1737,
        0.1737,
        0.1737
    ],
    "loss": [
        1.9432,
        1.9431,
        1.9429,
        1.9426,
        1.9424,
        1.9421,
        1.9419,
        1.9418,
        1.9416,
        1.9414,
        1.9413,
        1.9411,
        1.941,
        1.9407,
        1.9406
    ],
    "macro_f1": [
        0.0423,
        0.0423,
        0.0423,
        0.0423,
        0.0423,
        0.0423,
        0.0423,
        0.0423,
        0.0423,
        0.0423,
        0.0423,
        0.0423,
        0.0423,
        0.0423,
        0.0423
    ],
    "weighted_f1": [
        0.0514,
        0.0514,
        0.0514,
        0.0514,
        0.0514,
        0.0514,
        0.0514,
        0.0514,
        0.0514,
        0.0514,
        0.0514,
        0.0514,
        0.0514,
        0.0514,
        0.0514
    ],
    "macro_precision": [
        0.0248,
        0.0248,
        0.0248,
        0.0248,
        0.0248,
        0.0248,
        0.0248,
        0.0248,
        0.0248,
        0.0248,
        0.0248,
        0.0248,
        0.0248,
        0.0248,
        0.0248
    ],
    "macro_recall": [
        0.1429,
        0.1429,
        0.1429,
        0.1429,
        0.1429,
        0.1429,
        0.1429,
        0.1429,
        0.1429,
        0.1429,
        0.1429,
        0.1429,
        0.1429,
        0.1429,
        0.1429
    ],
    "per_class_f1_final": [
        0.0,
        0.0,
        0.0,
        0.0,
        0.296,
        0.0,
        0.0
    ],
    "emotion_names": [
        "Angry",
        "Disgust",
        "Fear",
        "Happy",
        "Sad",
        "Surprise",
        "Neutral"
    ],
    "confusion_matrix_final": [
        [
            0,
            0,
            0,
            0,
            958,
            0,
            0
        ],
        [
            0,
            0,
            0,
            0,
            111,
            0,
            0
        ],
        [
            0,
            0,
            0,
            0,
            1024,
            0,
            0
        ],
        [
            0,
            0,
            0,
            0,
            1774,
            0,
            0
        ],
        [
            0,
            0,
            0,
            0,
            1247,
            0,
            0
        ],
        [
            0,
            0,
            0,
            0,
            831,
            0,
            0
        ],
        [
            0,
            0,
            0,
            0,
            1233,
            0,
            0
        ]
    ],
    "dp_epsilon": [
        47.985,
        67.861,
        83.113,
        95.971,
        107.298,
        117.539,
        126.957,
        135.723,
        143.956,
        151.743,
        159.149,
        166.226,
        173.013,
        179.544,
        185.846
    ],
    "attack_detection_rate": [
        1.0,
        1.0,
        1.0,
        1.0,
        1.0,
        1.0,
        1.0,
        1.0,
        1.0,
        1.0,
        1.0,
        1.0,
        1.0,
        1.0,
        1.0
    ],
    "false_positive_rate": [
        0.0,
        0.0,
        0.0,
        0.0,
        0.0,
        0.0,
        0.0,
        0.0,
        0.0,
        0.0,
        0.0,
        0.0,
        0.0,
        0.0,
        0.0
    ],
    "total_clients": [
        5,
        5,
        5,
        5,
        5,
        5,
        5,
        5,
        5,
        5,
        5,
        5,
        5,
        5,
        5
    ],
    "anomalous_clients": [
        1,
        1,
        1,
        1,
        1,
        1,
        1,
        1,
        1,
        1,
        1,
        1,
        1,
        1,
        1
    ],
    "blocked_cids": [
        [
            "4"
        ],
        [
            "4"
        ],
        [
            "4"
        ],
        [
            "4"
        ],
        [
            "4"
        ],
        [
            "4"
        ],
        [
            "4"
        ],
        [
            "4"
        ],
        [
            "4"
        ],
        [
            "4"
        ],
        [
            "4"
        ],
        [
            "4"
        ],
        [
            "4"
        ],
        [
            "4"
        ],
        [
            "4"
        ]
    ],
    "communication_overhead_mb": [
        2.17,
        4.35,
        6.52,
        8.69,
        10.86,
        13.04,
        15.21,
        17.38,
        19.55,
        21.73,
        23.9,
        26.07,
        28.24,
        30.42,
        32.59
    ],
    "model_parameters": 56951,
    "model_size_mb": 0.22,
    "num_clients": 5,
    "local_epochs": 2,
    "learning_rate": 0.001,
    "batch_size": 64,
    "mu_fedprox": 0.01,
    "dp_enabled": true,
    "dp_norm_clip": 1.0,
    "dp_noise_multiplier": 0.1,
    "attacker_cid": "4",
    "attack_type": "sign_flip"
}